{
  "IsEncrypted": false,
  "Values": {
    "FUNCTIONS_INPROC_NET8_ENABLED": "true",
    "AzureWebJobsSchedule": "UseDevelopmentStorage=true",
    "FUNCTIONS_WORKER_RUNTIME": "dotnet-isolated",
    "SyncPropertiesTimerSchedule": "0 0 * * * *",
    "SyncMinerStatusTimerSchedule": "0 0 * * * *",
    "CalculatePropertyValuationsTimerSchedule": "0 0 * * * *",
    "SyncPropertyEstimatesTimerSchedule": "0 0 * * * *",
    "CalculatePropertyEstimateStatsTimerSchedule": "0 0 * * * *",
    "SyncValidatorStatusTimerSchedule": "* * * * * *",
    "UserKeyManagementTimerSchedule": "0 */1 * * * *",
    "RetryCount": 6
  }
}